risb/__init__.py
risb/helpers.py
risb/helpers_triqs.py
risb/solve_lattice.py
risb/version.py
risb/embedding/__init__.py
risb/embedding/dummy.py
risb/embedding/embedding_atom_diag.py
risb/kweight/__init__.py
risb/kweight/from_triqs_hartree.py
risb/kweight/kweight.py
risb/optimize/__init__.py
risb/optimize/diis.py
risb/optimize/linear_mixing.py
risb/optimize/solver_newton.py
risb-0.1.3.dist-info/METADATA
risb-0.1.3.dist-info/WHEEL
risb-0.1.3.dist-info/licenses/LICENSE
risb-0.1.3.dist-info/RECORD
