Metadata-Version: 2.4
Name: risb
Version: 0.1.3
Summary: Rotationally invariant slave boson mean-field theory.
Project-URL: Homepage, https://github.com/thenoursehorse/risb
Project-URL: Documentation, https://thenoursehorse.github.io/risb
Author: H. L. Nourse
License:                     GNU GENERAL PUBLIC LICENSE
License-File: LICENSE
Keywords: correlated electrons,mean field,quantum,quantum embedding,risb,slave bosons
Classifier: Intended Audience :: Science/Research
Classifier: License :: OSI Approved :: GNU General Public License v3 (GPLv3)
Classifier: Operating System :: OS Independent
Classifier: Programming Language :: Python :: 3
Classifier: Topic :: Scientific/Engineering :: Physics
Requires-Python: >=3.10
Requires-Dist: numpy
Requires-Dist: scipy
Provides-Extra: docs
Requires-Dist: furo; extra == 'docs'
Requires-Dist: myst-parser>=0.13; extra == 'docs'
Requires-Dist: myst-parser[linkify]; extra == 'docs'
Requires-Dist: sphinx-autobuild; extra == 'docs'
Requires-Dist: sphinx-autodoc-typehints; extra == 'docs'
Requires-Dist: sphinx-copybutton; extra == 'docs'
Requires-Dist: sphinx>=4.0; extra == 'docs'
Provides-Extra: test
Requires-Dist: h5py; extra == 'test'
Requires-Dist: pytest-subtests>=0.11; extra == 'test'
Requires-Dist: pytest>=7.0; extra == 'test'
